Metadata-Version: 2.1
Name: PyInsta-Scrape
Version: 1.0
Summary: A Python Package Which Scrapes Instagram Data
Home-page: https://github.com/BLUE-DEVIL1134/PyInsta
Author: Akash Pattnaik
Author-email: akashjio66666@gmail.com
License: UNKNOWN
Platform: UNKNOWN
Classifier: Programming Language :: Python :: 3
Classifier: License :: OSI Approved :: MIT License
Classifier: Operating System :: OS Independent
Requires-Python: >=3.7
